futilz/__init__.py
futilz-0.1.2.dist-info/LICENSE
futilz-0.1.2.dist-info/METADATA
futilz-0.1.2.dist-info/WHEEL
futilz-0.1.2.dist-info/top_level.txt
futilz-0.1.2.dist-info/RECORD
