Metadata-Version: 2.2
Name: futilz
Version: 0.1.2
Summary: A brief description of futilz
Home-page: https://github.com/Abdelmathin/futilz
Author: Abdelmathin Habachi
Author-email: abdelmathinhabachi@gmail.com
Classifier: Programming Language :: Python :: 3
Classifier: License :: OSI Approved :: MIT License
Classifier: Operating System :: OS Independent
Requires-Python: >=2.7
License-File: LICENSE
Dynamic: author
Dynamic: author-email
Dynamic: classifier
Dynamic: description
Dynamic: description-content-type
Dynamic: home-page
Dynamic: requires-python
Dynamic: summary
